wog/CurrencyRouletteGame.py
wog/Game.py
wog/GuessGame.py
wog/Live.py
wog/MainGame.py
wog/MemoryGame.py
wog/__init__.py
wog-1.1.0.2.dist-info/METADATA
wog-1.1.0.2.dist-info/WHEEL
wog-1.1.0.2.dist-info/top_level.txt
wog-1.1.0.2.dist-info/RECORD
