Metadata-Version: 2.1
Name: wog
Version: 1.1.0.2
Summary: A Package for DevOps course project.
Home-page: https://github.com/nissimuseri
Author: Nissim Museri
Author-email: nissim34@gmail.com
License: UNKNOWN
Platform: UNKNOWN
Classifier: Programming Language :: Python :: 3
Classifier: Operating System :: OS Independent
